bingefriend/shows/core/__init__.py
bingefriend/shows/core/config.py
bingefriend/shows/core/models/__init__.py
bingefriend/shows/core/models/base.py
bingefriend/shows/core/models/episode.py
bingefriend/shows/core/models/genre.py
bingefriend/shows/core/models/network.py
bingefriend/shows/core/models/season.py
bingefriend/shows/core/models/show.py
bingefriend/shows/core/models/show_genre.py
bingefriend/shows/core/models/web_channel.py
bingefriend_shows_core-0.2.8.dist-info/LICENSE
bingefriend_shows_core-0.2.8.dist-info/METADATA
bingefriend_shows_core-0.2.8.dist-info/WHEEL
bingefriend_shows_core-0.2.8.dist-info/RECORD
