Metadata-Version: 2.3
Name: bingefriend-shows-core
Version: 0.2.8
Summary: SQLAlchemy models for storing TV show data for BingeFriend.
License: MIT
Author: Tom Boone
Author-email: tbc@tomboone.com
Requires-Python: >=3.11
Classifier: License :: OSI Approved :: MIT License
Classifier: Programming Language :: Python :: 3
Classifier: Programming Language :: Python :: 3.11
Classifier: Programming Language :: Python :: 3.12
Classifier: Programming Language :: Python :: 3.13
Requires-Dist: sqlalchemy (>=2.0.40,<3.0.0)
